{
  "title": "Major development initiative in Thembalethu: Ilisolethu ",
  "description": "GEORGE NEWS -&nbsp;A development project for...",
  "link": "https://www.georgeherald.com/News/Article/Local-News/major-development-initiative-in-thembalethu-ilisolethu-202407230126",
  "updated": "2024-07-22T23:26:00.000Z",
  "section": "news",
  "category": "local-news",
  "isTopStory": false,
  "bodyText": "GEORGE NEWS - A development project for Thembalethu which aims to promote social, economic and residential development, and stimulate urban regeneration through investment projects, is currently underway.\n\n\n> George Municipality announced the Thembalethu Node Development Project earlier this week, branded \"Ilisolethu\", which means “Our Eye” in IsiXhosa. This initiative runs in partnership with National Treasury.\n\n\nThe idea is to create a vibrant and sustainable community hub in Thembalethu through new investments, which will stimulate economic growth in the precinct area along Nelson Mandela Boulevard (NMB), including the Thembalethu Central Business District (CBD).\n\nThe appointed service provider, Cadre Connect, drafted an Investment Strategy, an Area Management Strategy and identified 11 Investment Project Packages. The aim is to roll out the project over a 5-year period, subject to the availability of funding and commitment from investment partners.\n\n\n> Priority investment area\n\n\nThembalethu is a very densely populated suburb of George and has been identified as a priority investment area in the George Municipal Spatial Development Framework (MSDF) 2023, amongst other areas such as Blanco, the George CBD, Pacaltsdorp and other investment focus areas.\n\nThe Ilisolethu Precinct area is an area within Thembalethu classified as a mixed-use node where services and opportunities for all the residents of Thembalethu should be facilitated. The development area includes areas around the Thusong Centre, along Nelson Mandela Boulevard, from the N2 to just past 26th Avenue and available land between Nelson Mandela Boulevard and Ngcakani Road.\n\nGeorge Mayor Jackie Von Brandis said this initiative seeks to uplift the community of Thembalethu while creating a unique space for residents and visitors alike. “Some key benefits of this project include socio-economic opportunity, fostering of human potential, and creating a better, more accessible space for communal interaction and usage,” said Von Brandis.The Development Plan (Investment Plan and Area Management Strategy) has been adopted by the George Municipal Council and the Neighbourhood Development Partnership Programme team from National Treasury.Funding to initiate phased project implementation has been approved and the process to identify and engage investors has started.\n\nProject 7: This is what a market and outdoor gymnasium in Thembalethu might look like, through the Ilisolethu project.\n\n\n> The Ilisolethu precinct includes the following eleven projects:\n\n\nProject 1: Nelson Mandela Boulevard Multi-Purpose Identity Route\n\nThis project aims to redesign and upgrade Nelson Mandela Boulevard to improve traffic mobility and support public transport. It will also create a pedestrian-priority space, support Small, Medium, and Micro Enterprises (SMME) traders, and increase open spaces through pocket parks. Project 2: Ilisolethu Interchange Gateway Development\n\nThis development will provide economic opportunities through factory outlets and add residential options, creating a mixed-use, live-work-play node. It will serve as a landmark feature at the entrance of Thembalethu. High-density residential development opportunities will also be created. Project 3: Business Process Outsourcing (BPO) Village\n\nThe project aims to create a high-density, mixed-use activity core supporting economic opportunities and housing for working-class adults and students. The BPO (Business Process Outsourcing) intent aims to bring job opportunities to Thembalethu by creating spaces where third-party vendors or service providers can offer support functions for large corporates.\n\nProject 4: Dlabs, SafeHub Facility and Call Centre (Old Hospital / Clinic)\n\nThis precinct will address community needs through community-based solutions, including the establishment of a Safe Hub in partnership with the Development Bank of South Africa (DBSA) and Amandla. The intension is also to foster economic development and job creation, which will extend beyond support and training and will include a call centre. The Dlabs facility will also link to the development of sports initiatives and will include the construction of an artificial turf soccer field and sport-support facility on the Thembalethu Sports field as part of Project 7.\n\nProject 4: Dlabs, SafeHub Facility and Call Centre (Old Hospital / Clinic) Project 5: Inkcubeko (Embark in Knowledge) Youth and Science Centre Extension\n\nThe Centre plans to expand its services on additional Council land to include science and educational programs, additional classrooms, a Science, Technology, Engineering, and Mathematics (STEM) laboratory and an exhibition centre. Project 6: SMME (Small, Medium and Micro Enterprises) and Recycling Hub\n\nThis project will develop a trading space for trade in the vehicle industry and urban manufacturing and service trades, incorporating a recycling facility.\n\nProject 7: Park Run and Trim Park Recreation Route\n\nThe recreation route will integrate the area through a 5km recreational route for Park Run events, supporting a weekend market facility, upgrading of the existing sports field and multifunctional public open space. Project 8: NMB Multi-Purpose Public Open Spaces\n\nThis project aims to formalise two areas zoned for open space purposes into active parks and community spaces, and to redevelop encroaching informal settlement areas into micro-flat developments.\n\nProject 8: NMB Multi-Purpose Public Open Spaces Project 9: NMB Sports Node\n\nThe sports node relates to an undeveloped section of land along Nelson Mandela Boulevard and the development intent is to provide additional sports and recreational facilities, supporting community services and SMME trading facilities. Project 10: NMB SMME Trading Areas\n\nThis project will establish integrated and well-designed trading spaces, supporting the livelihoods of local traders. Project 11: Multimodal Transport and Social Cluster\n\nThe cluster will serve as a concentration point for social and community services, integrating non-motorized- and public transport modes within the sub-precinct design.\n\n‘We bring you the latest Garden Route, Hessequa, Karoo news’",
  "bodyHtml": "[{\"type\":\"paragraph\",\"text\":\"GEORGE NEWS - A development project for Thembalethu which aims to promote social, economic and residential development, and stimulate urban regeneration through investment projects, is currently underway.\",\"html\":\"GEORGE NEWS - A development project for Thembalethu which aims to promote social, economic and residential development, and stimulate urban regeneration through investment projects, is currently underway.\"},{\"type\":\"blockquote\",\"text\":\"George Municipality announced the Thembalethu Node Development Project earlier this week, branded \\\"Ilisolethu\\\", which means “Our Eye” in IsiXhosa. This initiative runs in partnership with National Treasury.\"},{\"type\":\"paragraph\",\"text\":\"The idea is to create a vibrant and sustainable community hub in Thembalethu through new investments, which will stimulate economic growth in the precinct area along Nelson Mandela Boulevard (NMB), including the Thembalethu Central Business District (CBD).\",\"html\":\"The idea is to create a vibrant and sustainable community hub in Thembalethu through new investments, which will stimulate economic growth in the precinct area along Nelson Mandela Boulevard (NMB), including the Thembalethu Central Business District (CBD).\"},{\"type\":\"paragraph\",\"text\":\"The appointed service provider, Cadre Connect, drafted an Investment Strategy, an Area Management Strategy and identified 11 Investment Project Packages. The aim is to roll out the project over a 5-year period, subject to the availability of funding and commitment from investment partners.\",\"html\":\"The appointed service provider, Cadre Connect, drafted an Investment Strategy, an Area Management Strategy and identified 11 Investment Project Packages. The aim is to roll out the project over a 5-year period, subject to the availability of funding and commitment from investment partners.\"},{\"type\":\"blockquote\",\"text\":\"Priority investment area\"},{\"type\":\"paragraph\",\"text\":\"Thembalethu is a very densely populated suburb of George and has been identified as a priority investment area in the George Municipal Spatial Development Framework (MSDF) 2023, amongst other areas such as Blanco, the George CBD, Pacaltsdorp and other investment focus areas.\",\"html\":\"Thembalethu is a very densely populated suburb of George and has been identified as a priority investment area in the George Municipal Spatial Development Framework (MSDF) 2023, amongst other areas such as Blanco, the George CBD, Pacaltsdorp and other investment focus areas.\"},{\"type\":\"paragraph\",\"text\":\"The Ilisolethu Precinct area is an area within Thembalethu classified as a mixed-use node where services and opportunities for all the residents of Thembalethu should be facilitated. The development area includes areas around the Thusong Centre, along Nelson Mandela Boulevard, from the N2 to just past 26th Avenue and available land between Nelson Mandela Boulevard and Ngcakani Road.\",\"html\":\"The Ilisolethu Precinct area is an area within Thembalethu classified as a mixed-use node where services and opportunities for all the residents of Thembalethu should be facilitated. The development area includes areas around the Thusong Centre, along Nelson Mandela Boulevard, from the N2 to just past 26th Avenue and available land between Nelson Mandela Boulevard and Ngcakani Road.\"},{\"type\":\"paragraph\",\"text\":\"George Mayor Jackie Von Brandis said this initiative seeks to uplift the community of Thembalethu while creating a unique space for residents and visitors alike. “Some key benefits of this project include socio-economic opportunity, fostering of human potential, and creating a better, more accessible space for communal interaction and usage,” said Von Brandis.The Development Plan (Investment Plan and Area Management Strategy) has been adopted by the George Municipal Council and the Neighbourhood Development Partnership Programme team from National Treasury.Funding to initiate phased project implementation has been approved and the process to identify and engage investors has started.\",\"html\":\"George Mayor Jackie Von Brandis said this initiative seeks to uplift the community of Thembalethu while creating a unique space for residents and visitors alike. “Some key benefits of this project include socio-economic opportunity, fostering of human potential, and creating a better, more accessible space for communal interaction and usage,” said Von Brandis.<br><br>The Development Plan (Investment Plan and Area Management Strategy) has been adopted by the George Municipal Council and the Neighbourhood Development Partnership Programme team from National Treasury.<br>Funding to initiate phased project implementation has been approved and the process to identify and engage investors has started.\"},{\"type\":\"paragraph\",\"text\":\"Project 7: This is what a market and outdoor gymnasium in Thembalethu might look like, through the Ilisolethu project.\",\"html\":\"<span class=\\\"fr-img-caption fr-fic fr-dib class1\\\" style=\\\"width: 696px;\\\"><span class=\\\"fr-img-wrap\\\"><img src=\\\"https://cms.groupeditors.com//media/1/1///fcb04f64-ef1e-47d8-a474-be476df22abd.jpg\\\"><span class=\\\"fr-inner\\\">Project 7: This is what a market and outdoor gymnasium in Thembalethu might look like, through the Ilisolethu project. </span></span></span>\"},{\"type\":\"blockquote\",\"text\":\"The Ilisolethu precinct includes the following eleven projects:\"},{\"type\":\"paragraph\",\"text\":\"Project 1: Nelson Mandela Boulevard Multi-Purpose Identity Route\",\"html\":\"<strong>Project 1: Nelson Mandela Boulevard Multi-Purpose Identity Route</strong>\"},{\"type\":\"paragraph\",\"text\":\"This project aims to redesign and upgrade Nelson Mandela Boulevard to improve traffic mobility and support public transport. It will also create a pedestrian-priority space, support Small, Medium, and Micro Enterprises (SMME) traders, and increase open spaces through pocket parks. Project 2: Ilisolethu Interchange Gateway Development\",\"html\":\"This project aims to redesign and upgrade Nelson Mandela Boulevard to improve traffic mobility and support public transport. It will also create a pedestrian-priority space, support Small, Medium, and Micro Enterprises (SMME) traders, and increase open spaces through pocket parks.<br> <br><strong>Project 2: Ilisolethu Interchange Gateway Development</strong>\"},{\"type\":\"paragraph\",\"text\":\"This development will provide economic opportunities through factory outlets and add residential options, creating a mixed-use, live-work-play node. It will serve as a landmark feature at the entrance of Thembalethu. High-density residential development opportunities will also be created. Project 3: Business Process Outsourcing (BPO) Village\",\"html\":\"This development will provide economic opportunities through factory outlets and add residential options, creating a mixed-use, live-work-play node. It will serve as a landmark feature at the entrance of Thembalethu. High-density residential development opportunities will also be created.<br> <br><strong>Project 3: Business Process Outsourcing (BPO) Village</strong>\"},{\"type\":\"paragraph\",\"text\":\"The project aims to create a high-density, mixed-use activity core supporting economic opportunities and housing for working-class adults and students. The BPO (Business Process Outsourcing) intent aims to bring job opportunities to Thembalethu by creating spaces where third-party vendors or service providers can offer support functions for large corporates.\",\"html\":\"The project aims to create a high-density, mixed-use activity core supporting economic opportunities and housing for working-class adults and students. The BPO (Business Process Outsourcing) intent aims to bring job opportunities to Thembalethu by creating spaces where third-party vendors or service providers can offer support functions for large corporates.\"},{\"type\":\"paragraph\",\"text\":\"Project 4: Dlabs, SafeHub Facility and Call Centre (Old Hospital / Clinic)\",\"html\":\"<strong>Project 4: Dlabs, SafeHub Facility and Call Centre (Old Hospital / Clinic)</strong>\"},{\"type\":\"paragraph\",\"text\":\"This precinct will address community needs through community-based solutions, including the establishment of a Safe Hub in partnership with the Development Bank of South Africa (DBSA) and Amandla. The intension is also to foster economic development and job creation, which will extend beyond support and training and will include a call centre. The Dlabs facility will also link to the development of sports initiatives and will include the construction of an artificial turf soccer field and sport-support facility on the Thembalethu Sports field as part of Project 7.\",\"html\":\"This precinct will address community needs through community-based solutions, including the establishment of a Safe Hub in partnership with the Development Bank of South Africa (DBSA) and Amandla. The intension is also to foster economic development and job creation, which will extend beyond support and training and will include a call centre. The Dlabs facility will also link to the development of sports initiatives and will include the construction of an artificial turf soccer field and sport-support facility on the Thembalethu Sports field as part of Project 7.\"},{\"type\":\"paragraph\",\"text\":\"Project 4: Dlabs, SafeHub Facility and Call Centre (Old Hospital / Clinic) Project 5: Inkcubeko (Embark in Knowledge) Youth and Science Centre Extension\",\"html\":\"<span class=\\\"fr-img-caption fr-fic fr-dib class1\\\" style=\\\"width: 696px;\\\"><span class=\\\"fr-img-wrap\\\"><img src=\\\"https://cms.groupeditors.com//media/1/1///dc1cc934-b56e-42a6-a6ad-3235c99881c7.jpg\\\"><span class=\\\"fr-inner\\\">Project 4: Dlabs, SafeHub Facility and Call Centre (Old Hospital / Clinic)</span></span></span> <strong>Project 5: Inkcubeko (Embark in Knowledge) Youth and Science Centre Extension</strong>\"},{\"type\":\"paragraph\",\"text\":\"The Centre plans to expand its services on additional Council land to include science and educational programs, additional classrooms, a Science, Technology, Engineering, and Mathematics (STEM) laboratory and an exhibition centre. Project 6: SMME (Small, Medium and Micro Enterprises) and Recycling Hub\",\"html\":\"The Centre plans to expand its services on additional Council land to include science and educational programs, additional classrooms, a Science, Technology, Engineering, and Mathematics (STEM) laboratory and an exhibition centre.<br> <br><strong>Project 6: SMME (Small, Medium and Micro Enterprises) and Recycling Hub</strong>\"},{\"type\":\"paragraph\",\"text\":\"This project will develop a trading space for trade in the vehicle industry and urban manufacturing and service trades, incorporating a recycling facility.\",\"html\":\"This project will develop a trading space for trade in the vehicle industry and urban manufacturing and service trades, incorporating a recycling facility.\"},{\"type\":\"paragraph\",\"text\":\"Project 7: Park Run and Trim Park Recreation Route\",\"html\":\"<br><strong>Project 7: Park Run and Trim Park Recreation Route</strong>\"},{\"type\":\"paragraph\",\"text\":\"The recreation route will integrate the area through a 5km recreational route for Park Run events, supporting a weekend market facility, upgrading of the existing sports field and multifunctional public open space. Project 8: NMB Multi-Purpose Public Open Spaces\",\"html\":\"The recreation route will integrate the area through a 5km recreational route for Park Run events, supporting a weekend market facility, upgrading of the existing sports field and multifunctional public open space.<br> <br><strong>Project 8: NMB Multi-Purpose Public Open Spaces</strong>\"},{\"type\":\"paragraph\",\"text\":\"This project aims to formalise two areas zoned for open space purposes into active parks and community spaces, and to redevelop encroaching informal settlement areas into micro-flat developments.\",\"html\":\"This project aims to formalise two areas zoned for open space purposes into active parks and community spaces, and to redevelop encroaching informal settlement areas into micro-flat developments.\"},{\"type\":\"paragraph\",\"text\":\"Project 8: NMB Multi-Purpose Public Open Spaces Project 9: NMB Sports Node\",\"html\":\"<span class=\\\"fr-img-caption fr-fic fr-dib class1\\\" style=\\\"width: 610px;\\\"><span class=\\\"fr-img-wrap\\\"><img src=\\\"https://cms.groupeditors.com//media/1/1///2771e069-fad5-484e-b216-ac8b110ece3d.png\\\"><span class=\\\"fr-inner\\\">Project 8: NMB Multi-Purpose Public Open Spaces</span></span></span> <strong>Project 9: NMB Sports Node</strong>\"},{\"type\":\"paragraph\",\"text\":\"The sports node relates to an undeveloped section of land along Nelson Mandela Boulevard and the development intent is to provide additional sports and recreational facilities, supporting community services and SMME trading facilities. Project 10: NMB SMME Trading Areas\",\"html\":\"The sports node relates to an undeveloped section of land along Nelson Mandela Boulevard and the development intent is to provide additional sports and recreational facilities, supporting community services and SMME trading facilities.<br> <br><strong>Project 10: NMB SMME Trading Areas</strong>\"},{\"type\":\"paragraph\",\"text\":\"This project will establish integrated and well-designed trading spaces, supporting the livelihoods of local traders. Project 11: Multimodal Transport and Social Cluster\",\"html\":\"This project will establish integrated and well-designed trading spaces, supporting the livelihoods of local traders.<br> <br><strong>Project 11: Multimodal Transport and Social Cluster</strong>\"},{\"type\":\"paragraph\",\"text\":\"The cluster will serve as a concentration point for social and community services, integrating non-motorized- and public transport modes within the sub-precinct design.\",\"html\":\"The cluster will serve as a concentration point for social and community services, integrating non-motorized- and public transport modes within the sub-precinct design.\"},{\"type\":\"paragraph\",\"text\":\"‘We bring you the latest Garden Route, Hessequa, Karoo news’\",\"html\":\"<strong fr-original-style=\\\"\\\" style=\\\"font-weight: bold; box-sizing: border-box;\\\"><em fr-original-style=\\\"\\\" style=\\\"box-sizing: border-box;\\\">‘We bring you the latest Garden Route, Hessequa, Karoo news’</em></strong>\"}]",
  "images": [
    {
      "url": "https://cms.groupeditors.com/img/e69cb77f-9c13-4b32-b334-b1785c0325d0.jpg?w=400&scale=both&quality=100",
      "alt": "Major development initiative in Thembalethu: Ilisolethu "
    },
    {
      "url": "https://cms.groupeditors.com//media/1/1///fcb04f64-ef1e-47d8-a474-be476df22abd.jpg",
      "alt": ""
    },
    {
      "url": "https://cms.groupeditors.com//media/1/1///dc1cc934-b56e-42a6-a6ad-3235c99881c7.jpg",
      "alt": ""
    },
    {
      "url": "https://cms.groupeditors.com//media/1/1///2771e069-fad5-484e-b216-ac8b110ece3d.png",
      "alt": ""
    }
  ],
  "author": "",
  "tags": [],
  "videoUrls": [],
  "galleryLink": "/Galleries/General",
  "ogImage": "https://cms.groupeditors.com/img/e69cb77f-9c13-4b32-b334-b1785c0325d0.jpg?crop=133,0,794,372",
  "workspace": "george-herald"
}