{
  "title": "Tupperware to officially close shop in SA. What are your best memories?",
  "description": "BUSINESS NEWS - Tupperware, South...",
  "link": "https://www.georgeherald.com/News/Article/Business/tupperware-to-officially-close-shop-in-sa-what-are-your-best-memories-202412111235",
  "updated": "2024-12-11T10:35:00.000Z",
  "section": "news",
  "category": "business",
  "isTopStory": false,
  "bodyText": "BUSINESS NEWS - Tupperware, South Africa’s beloved container brand, will officially close its doors in the country at the end of the year, leaving behind many unforgettable memories.\n\nTupperware has announced to its stakeholders in SA that the brand will cease to exist, including employees who were served with Voluntary Severance Packages, with service expected to end on 31 December 2024.\n\nTupperware’s operations will close in SA and Australia. But operations are set to continue in other markets.\n\nThe brand can be found on display or inside kitchen cupboards of many households in the country, with each person having a different story to tell.\n\n\n> Tupperware distributors\n\n\nWhether it is a father and his children who were forbidden from using the containers because they often lost them, or the mother who distributed Tupperware to earn extra money, the brand forms part of many South Africans’ stories.\n\nMartha Mothupi, who used to be a distributor for Tupperware for almost nine years told The Citizen the best part about selling the products was the demonstration luncheons they used to host.\n\nA group of women who sold Tupperware would visit one woman’s house and call others who were interested to buy or join in selling the products.\n\n\n> Tupperware parties\n\n\nAt these luncheons, different new-in-the-market products would be demonstrated, with actual food and drinks to be enjoyed later, to get people to buy.\n\nMothupi said these luncheons were not only about demonstrating products but also great for her social life because she and others were able to catch up.\n\n\n> Tupperware’s founder\n\n\nTupperware was founded in the early 1940s by Earl Tupper.\n\nThe brand’s website said, “The first consumer plastic products were Wonderlier Bowel and Bell Tumbler offered a unique benefit that traditional food containers did not: they were lighter and less likely to break than traditional glass and crockery.”\n\n“With the onset of the post-war ‘baby boom’, women dedicated themselves to caring for their growing families.\n\n“The ‘Tupperized’ kitchen was born … a kitchen that was well organised and neat, and featured a variety of containers that replaced unsightly open packages and that kept food fresh longer.”\n\n\n> Making extra money\n\n\nAnother distributor, Pulane Koteli, told The Citizen that they were able to earn a commission from the sales they made. If she made a lot of sales during the month, the commission would look impressive.\n\nHowever, she said she used this commission to buy herself more Tupperware products, instead of using it on other brands.\n\nKoteli expressed her love for the products due to their versatility, great value for money, and high quality.\n\n\n> Is the brand loved by new generation?\n\n\nPapali Rantsoareng recalled how there was a point when her mother did not allow her to make use of the containers because she would always misplace them at school.\n\nHowever, she told The Citizen that she would use the products because they were available at home. Now that she is older, she does not see herself investing as much in the brand as her mother did.\n\n“I will buy any great quality containers I can find at the store, and I would still be able to use them for lunch to work, to keep leftover food fresh and other stuff.”\n\n\n> The brand’s closure\n\n\nTupperware was introduced in Southern Africa in 1964, with today having over 270 000 consultants forming part of the company.\n\nIn September of this year, Tupperware filed for bankruptcy, legally known as Chapter 11 proceedings in the United States Bankruptcy Court for the District of Delaware.\n\nPresident and Chief Executive Officer of Tupperware Brands Corporation, Laurie Ann Goldman said they found themselves in a difficult financial position due to the challenging macroeconomic environment.\n\nAt the time, she said they had looked at several strategic options, and filing for bankruptcy was the best path forward.\n\n“This process is meant to provide us with essential flexibility as we pursue strategic alternatives to support our transformation into a digital-first, technology-led company better positioned to serve our stakeholders.”\n\n\n> 31 December 2024 – end of an era\n\n\nTupperware Southern Africa recently announced to distributors and independent sales forces its intent to shut operations in the country.\n\nIn a letter, the brand said given the news that part of the business has been bought, SA is not included in the deal.\n\nThe letter adds that it seems SA will not be given any equipment by Tupperware to manufacture products.\n\n“Since Tupperware Southern Africa has not received any equipment to continue to create a December or any future product campaigns, there is only a limited quantity and range of stock available for sale to your distributors.”\n\n\n> SA sidelined\n\n\nThe decision to issue Voluntary Severance Packages to employees was motivated by the lack of confirmation that the SA operations will be receiving the license agreement and equipment to continue operating.\n\nOperations will come to an end on 31 December 2024. Those who would have not accepted the Severance Packages by then will be retrenched from January 2025.\n\n“At this stage, the board of directors and management are waiting for final instructions from the company’s shareholders and are further taking legal advice as to how to manage the current situation.”\n\nGoldman announced that the New Tupperware Company will focus on global core markets including the United States, Canada, Mexico, Brazil, China, Korea, India, and Malaysia, and the new company intends to follow on with European and additional Asian markets.\n\nArticle: Caxton publication, The Citizen\n\n‘We bring you the latest Garden Route, Hessequa, Karoo news’",
  "bodyHtml": "[{\"type\":\"paragraph\",\"text\":\"BUSINESS NEWS - Tupperware, South Africa’s beloved container brand, will officially close its doors in the country at the end of the year, leaving behind many unforgettable memories.\",\"html\":\"BUSINESS NEWS - Tupperware, South Africa’s beloved container brand, will officially close its doors in the country at the end of the year, leaving behind many unforgettable memories.\"},{\"type\":\"paragraph\",\"text\":\"Tupperware has announced to its stakeholders in SA that the brand will cease to exist, including employees who were served with Voluntary Severance Packages, with service expected to end on 31 December 2024.\",\"html\":\"Tupperware has announced to its stakeholders in SA that the brand will cease to exist, including employees who were served with Voluntary Severance Packages, with service expected to end on 31 December 2024.\"},{\"type\":\"paragraph\",\"text\":\"Tupperware’s operations will close in SA and Australia. But operations are set to continue in other markets.\",\"html\":\"Tupperware’s operations will close in SA and Australia. But operations are set to continue in other markets.\"},{\"type\":\"paragraph\",\"text\":\"The brand can be found on display or inside kitchen cupboards of many households in the country, with each person having a different story to tell.\",\"html\":\"The brand can be found on display or inside kitchen cupboards of many households in the country, with each person having a different story to tell.\"},{\"type\":\"blockquote\",\"text\":\"Tupperware distributors\"},{\"type\":\"paragraph\",\"text\":\"Whether it is a father and his children who were forbidden from using the containers because they often lost them, or the mother who distributed Tupperware to earn extra money, the brand forms part of many South Africans’ stories.\",\"html\":\"Whether it is a father and his children who were forbidden from using the containers because they often lost them, or the mother who distributed Tupperware to earn extra money, the brand forms part of many South Africans’ stories.\"},{\"type\":\"paragraph\",\"text\":\"Martha Mothupi, who used to be a distributor for Tupperware for almost nine years told The Citizen the best part about selling the products was the demonstration luncheons they used to host.\",\"html\":\"Martha Mothupi, who used to be a distributor for Tupperware for almost nine years told <em>The Citizen</em> the best part about selling the products was the demonstration luncheons they used to host.\"},{\"type\":\"paragraph\",\"text\":\"A group of women who sold Tupperware would visit one woman’s house and call others who were interested to buy or join in selling the products.\",\"html\":\"A group of women who sold Tupperware would visit one woman’s house and call others who were interested to buy or join in selling the products.\"},{\"type\":\"blockquote\",\"text\":\"Tupperware parties\"},{\"type\":\"paragraph\",\"text\":\"At these luncheons, different new-in-the-market products would be demonstrated, with actual food and drinks to be enjoyed later, to get people to buy.\",\"html\":\"At these luncheons, different new-in-the-market products would be demonstrated, with actual food and drinks to be enjoyed later, to get people to buy.\"},{\"type\":\"paragraph\",\"text\":\"Mothupi said these luncheons were not only about demonstrating products but also great for her social life because she and others were able to catch up.\",\"html\":\"Mothupi said these luncheons were not only about demonstrating products but also great for her social life because she and others were able to catch up.\"},{\"type\":\"blockquote\",\"text\":\"Tupperware’s founder\"},{\"type\":\"paragraph\",\"text\":\"Tupperware was founded in the early 1940s by Earl Tupper.\",\"html\":\"Tupperware was founded in the early 1940s by Earl Tupper.\"},{\"type\":\"paragraph\",\"text\":\"The brand’s website said, “The first consumer plastic products were Wonderlier Bowel and Bell Tumbler offered a unique benefit that traditional food containers did not: they were lighter and less likely to break than traditional glass and crockery.”\",\"html\":\"The brand’s <a href=\\\"https://www.tupperware.co.za/about-us\\\" rel=\\\"nofollow noopener noreferrer\\\" target=\\\"_blank\\\">website</a> said, “The first consumer plastic products were Wonderlier Bowel and Bell Tumbler offered a unique benefit that traditional food containers did not: they were lighter and less likely to break than traditional glass and crockery.”\"},{\"type\":\"paragraph\",\"text\":\"“With the onset of the post-war ‘baby boom’, women dedicated themselves to caring for their growing families.\",\"html\":\"“With the onset of the post-war ‘baby boom’, women dedicated themselves to caring for their growing families.\"},{\"type\":\"paragraph\",\"text\":\"“The ‘Tupperized’ kitchen was born … a kitchen that was well organised and neat, and featured a variety of containers that replaced unsightly open packages and that kept food fresh longer.”\",\"html\":\"“The ‘Tupperized’ kitchen was born … a kitchen that was well organised and neat, and featured a variety of containers that replaced unsightly open packages and that kept food fresh longer.”\"},{\"type\":\"blockquote\",\"text\":\"Making extra money\"},{\"type\":\"paragraph\",\"text\":\"Another distributor, Pulane Koteli, told The Citizen that they were able to earn a commission from the sales they made. If she made a lot of sales during the month, the commission would look impressive.\",\"html\":\"Another distributor, Pulane Koteli, told The Citizen that they were able to earn a commission from the sales they made. If she made a lot of sales during the month, the commission would look impressive.\"},{\"type\":\"paragraph\",\"text\":\"However, she said she used this commission to buy herself more Tupperware products, instead of using it on other brands.\",\"html\":\"However, she said she used this commission to buy herself more Tupperware products, instead of using it on other brands.\"},{\"type\":\"paragraph\",\"text\":\"Koteli expressed her love for the products due to their versatility, great value for money, and high quality.\",\"html\":\"Koteli expressed her love for the products due to their versatility, great value for money, and high quality.\"},{\"type\":\"blockquote\",\"text\":\"Is the brand loved by new generation?\"},{\"type\":\"paragraph\",\"text\":\"Papali Rantsoareng recalled how there was a point when her mother did not allow her to make use of the containers because she would always misplace them at school.\",\"html\":\"Papali Rantsoareng recalled how there was a point when her mother did not allow her to make use of the containers because she would always misplace them at school.\"},{\"type\":\"paragraph\",\"text\":\"However, she told The Citizen that she would use the products because they were available at home. Now that she is older, she does not see herself investing as much in the brand as her mother did.\",\"html\":\"However, she told The Citizen that she would use the products because they were available at home. Now that she is older, she does not see herself investing as much in the brand as her mother did.\"},{\"type\":\"paragraph\",\"text\":\"“I will buy any great quality containers I can find at the store, and I would still be able to use them for lunch to work, to keep leftover food fresh and other stuff.”\",\"html\":\"“I will buy any great quality containers I can find at the store, and I would still be able to use them for lunch to work, to keep leftover food fresh and other stuff.”\"},{\"type\":\"blockquote\",\"text\":\"The brand’s closure\"},{\"type\":\"paragraph\",\"text\":\"Tupperware was introduced in Southern Africa in 1964, with today having over 270 000 consultants forming part of the company.\",\"html\":\"Tupperware was introduced in Southern Africa in 1964, with today having over 270 000 consultants forming part of the company.\"},{\"type\":\"paragraph\",\"text\":\"In September of this year, Tupperware filed for bankruptcy, legally known as Chapter 11 proceedings in the United States Bankruptcy Court for the District of Delaware.\",\"html\":\"In September of this year, Tupperware filed for bankruptcy, legally known as Chapter 11 proceedings in the United States Bankruptcy Court for the District of Delaware.\"},{\"type\":\"paragraph\",\"text\":\"President and Chief Executive Officer of Tupperware Brands Corporation, Laurie Ann Goldman said they found themselves in a difficult financial position due to the challenging macroeconomic environment.\",\"html\":\"President and Chief Executive Officer of Tupperware Brands Corporation, Laurie Ann Goldman said they found themselves in a difficult financial position due to the challenging macroeconomic environment.\"},{\"type\":\"paragraph\",\"text\":\"At the time, she said they had looked at several strategic options, and filing for bankruptcy was the best path forward.\",\"html\":\"At the time, she said they had looked at several strategic options, and filing for bankruptcy was the best path forward.\"},{\"type\":\"paragraph\",\"text\":\"“This process is meant to provide us with essential flexibility as we pursue strategic alternatives to support our transformation into a digital-first, technology-led company better positioned to serve our stakeholders.”\",\"html\":\"“This process is meant to provide us with essential flexibility as we pursue strategic alternatives to support our transformation into a digital-first, technology-led company better positioned to serve our stakeholders.”\"},{\"type\":\"blockquote\",\"text\":\"31 December 2024 – end of an era\"},{\"type\":\"paragraph\",\"text\":\"Tupperware Southern Africa recently announced to distributors and independent sales forces its intent to shut operations in the country.\",\"html\":\"Tupperware Southern Africa recently announced to distributors and independent sales forces its intent to shut operations in the country.\"},{\"type\":\"paragraph\",\"text\":\"In a letter, the brand said given the news that part of the business has been bought, SA is not included in the deal.\",\"html\":\"In a letter, the brand said given the news that part of the business has been bought, SA is not included in the deal.\"},{\"type\":\"paragraph\",\"text\":\"The letter adds that it seems SA will not be given any equipment by Tupperware to manufacture products.\",\"html\":\"The letter adds that it seems SA will not be given any equipment by Tupperware to manufacture products.\"},{\"type\":\"paragraph\",\"text\":\"“Since Tupperware Southern Africa has not received any equipment to continue to create a December or any future product campaigns, there is only a limited quantity and range of stock available for sale to your distributors.”\",\"html\":\"“Since Tupperware Southern Africa has not received any equipment to continue to create a December or any future product campaigns, there is only a limited quantity and range of stock available for sale to your distributors.”\"},{\"type\":\"blockquote\",\"text\":\"SA sidelined\"},{\"type\":\"paragraph\",\"text\":\"The decision to issue Voluntary Severance Packages to employees was motivated by the lack of confirmation that the SA operations will be receiving the license agreement and equipment to continue operating.\",\"html\":\"The decision to issue Voluntary Severance Packages to employees was motivated by the lack of confirmation that the SA operations will be receiving the license agreement and equipment to continue operating.\"},{\"type\":\"paragraph\",\"text\":\"Operations will come to an end on 31 December 2024. Those who would have not accepted the Severance Packages by then will be retrenched from January 2025.\",\"html\":\"Operations will come to an end on 31 December 2024. Those who would have not accepted the Severance Packages by then will be retrenched from January 2025.\"},{\"type\":\"paragraph\",\"text\":\"“At this stage, the board of directors and management are waiting for final instructions from the company’s shareholders and are further taking legal advice as to how to manage the current situation.”\",\"html\":\"“At this stage, the board of directors and management are waiting for final instructions from the company’s shareholders and are further taking legal advice as to how to manage the current situation.”\"},{\"type\":\"paragraph\",\"text\":\"Goldman announced that the New Tupperware Company will focus on global core markets including the United States, Canada, Mexico, Brazil, China, Korea, India, and Malaysia, and the new company intends to follow on with European and additional Asian markets.\",\"html\":\"Goldman announced that the <a href=\\\"https://ir.tupperwarebrands.com/news-and-events/press-releases/2024/10-22-2024\\\" rel=\\\"nofollow noopener noreferrer\\\" target=\\\"_blank\\\">New Tupperware Company</a> will focus on global core markets including the United States, Canada, Mexico, Brazil, China, Korea, India, and Malaysia, and the new company intends to follow on with European and additional Asian markets.\"},{\"type\":\"paragraph\",\"text\":\"Article: Caxton publication, The Citizen\",\"html\":\"<a href=\\\"https://www.citizen.co.za/business/tupperware-to-officially-close-shop-in-sa-what-are-your-best-memories/\\\" rel=\\\"noopener noreferrer\\\" target=\\\"_blank\\\">Article: Caxton publication, The Citizen</a>\"},{\"type\":\"paragraph\",\"text\":\"‘We bring you the latest Garden Route, Hessequa, Karoo news’\",\"html\":\"<strong fr-original-style=\\\"\\\" style=\\\"font-weight: bold; box-sizing: border-box;\\\"><em fr-original-style=\\\"\\\" style=\\\"box-sizing: border-box;\\\">‘We bring you the latest Garden Route, Hessequa, Karoo news’</em></strong>\"}]",
  "images": [
    {
      "url": "https://cms.groupeditors.com/img/267ab518-f5b2-4803-ba0b-8907a0ea3023.jpg?w=400&scale=both&quality=100",
      "alt": "Tupperware to officially close shop in SA. What are your best memories?"
    }
  ],
  "author": "",
  "tags": [],
  "videoUrls": [],
  "galleryLink": "/Galleries/General",
  "ogImage": "https://cms.groupeditors.com/img/267ab518-f5b2-4803-ba0b-8907a0ea3023.jpg?crop=0,278,400,503",
  "workspace": "george-herald"
}